k4a/__init__.py
k4a/enumstruct.py
k4a/pyk4a.py
k4a/pyk4abt.py
k4a-0.0.1.dist-info/METADATA
k4a-0.0.1.dist-info/WHEEL
k4a-0.0.1.dist-info/top_level.txt
k4a-0.0.1.dist-info/RECORD
