Metadata-Version: 2.1
Name: k4a
Version: 0.0.1
Summary: Python 3 bindings for the Azure Kinect SDK
Home-page: https://github.com/hexops/Azure-Kinect-Python
Author: The HexOps Authors
Author-email: stephen.gutekanst@gmail.com
License: UNKNOWN
Platform: UNKNOWN
Classifier: Programming Language :: Python :: 3
Classifier: License :: OSI Approved :: MIT License
Classifier: Operating System :: OS Independent
Requires-Python: >=3.6
